MediaSwiftPy/__init__.py
MediaSwiftPy/ffpe.py
MediaSwiftPy/ffpl.py
MediaSwiftPy/ffpr.py
MediaSwiftPy/bin/ffmpeg.exe
MediaSwiftPy/bin/ffplay.exe
MediaSwiftPy/bin/ffprobe.exe
MediaSwiftPy-2.1.1.dist-info/METADATA
MediaSwiftPy-2.1.1.dist-info/WHEEL
MediaSwiftPy-2.1.1.dist-info/entry_points.txt
MediaSwiftPy-2.1.1.dist-info/license.txt
MediaSwiftPy-2.1.1.dist-info/top_level.txt
MediaSwiftPy-2.1.1.dist-info/RECORD
