Metadata-Version: 2.1
Name: MediaSwiftPy
Version: 2.1.1
Summary: A PYTHON PACKAGE FOR VIDEO CONVERSION AND PROBING USING MediaSwiftPy FFPLAY AND FFPROBE.
Home-page: https://github.com/ROHIT-SINGH-1
Author: ROHIT SINGH
Author-email: rs3232263@gmail.com
License: GPL-3.0
Classifier: Programming Language :: Python :: 3
Classifier: License :: OSI Approved :: GNU General Public License v3 (GPLv3)
Classifier: Operating System :: OS Independent
Requires-Python: >=3.9
License-File: license.txt
